pcoss_scheduler_pkg/__init__.py
pcoss_scheduler_pkg/__main__.py
pcoss_scheduler_pkg/algorithms.py
pcoss_scheduler_pkg/constants.py
pcoss_scheduler_pkg/helpers.py
pcoss_scheduler_pkg/main.py
pcoss_scheduler_pkg/operations.py
pcoss_scheduler_pkg/output.py
pcoss_scheduler_pkg/problem_input.py
pcoss_scheduler_pkg/scheduler.py
pcoss_scheduler_pkg_ksazon-0.0.25.dist-info/LICENSE
pcoss_scheduler_pkg_ksazon-0.0.25.dist-info/METADATA
pcoss_scheduler_pkg_ksazon-0.0.25.dist-info/WHEEL
pcoss_scheduler_pkg_ksazon-0.0.25.dist-info/top_level.txt
pcoss_scheduler_pkg_ksazon-0.0.25.dist-info/RECORD
